pywincompiler/__init__.py
pywincompiler-0.9.0.dist-info/METADATA
pywincompiler-0.9.0.dist-info/WHEEL
pywincompiler-0.9.0.dist-info/top_level.txt
pywincompiler-0.9.0.dist-info/RECORD
