Metadata-Version: 2.1
Name: pywincompiler
Version: 0.9.0
Summary: Python exe compiler
Author: John
Author-email: eesfesfs@fsesefsef.fsefessfe
Keywords: python
Classifier: Operating System :: Microsoft :: Windows
